voice_status_report_mcp_server/__init__.py
voice_status_report_mcp_server/ding.aiff
voice_status_report_mcp_server/py.typed
voice_status_report_mcp_server/server.py
voice_status_report_mcp_server-0.1.3.dist-info/METADATA
voice_status_report_mcp_server-0.1.3.dist-info/WHEEL
voice_status_report_mcp_server-0.1.3.dist-info/entry_points.txt
voice_status_report_mcp_server-0.1.3.dist-info/licenses/LICENSE
voice_status_report_mcp_server-0.1.3.dist-info/RECORD
