Metadata-Version: 2.4
Name: voice-status-report-mcp-server
Version: 0.1.3
Summary: An MCP server providing voice status reports using OpenAI TTS (text-to-speech) API
Author-email: Tomek Korbak <tomasz.korbak@gmail.com>
License-File: LICENSE
Requires-Python: >=3.12
Requires-Dist: click>=8.1.0
Requires-Dist: mcp>=1.5.0
Requires-Dist: openai>=1.68.2
Requires-Dist: pydub>=0.25.1
Requires-Dist: typing-extensions>=4.0.0
